anomalylab/__init__.py
anomalylab/config.py
anomalylab/core/__init__.py
anomalylab/core/core.py
anomalylab/datasets/__init__.py
anomalylab/datasets/dataset.py
anomalylab/datasets/panel_data.csv
anomalylab/datasets/time_series_data.csv
anomalylab/empirical/__init__.py
anomalylab/empirical/correlation.py
anomalylab/empirical/empirical.py
anomalylab/empirical/fm_regression.py
anomalylab/empirical/persistence.py
anomalylab/empirical/portfolio.py
anomalylab/empirical/summary.py
anomalylab/preprocess/__init__.py
anomalylab/preprocess/fillna.py
anomalylab/preprocess/normalize.py
anomalylab/preprocess/preprocessor.py
anomalylab/preprocess/shift.py
anomalylab/preprocess/winsorize.py
anomalylab/structure/__init__.py
anomalylab/structure/data.py
anomalylab/structure/panel_data.py
anomalylab/structure/time_series.py
anomalylab/utils/__init__.py
anomalylab/utils/imports.py
anomalylab/utils/utils.py
anomalylab/visualization/__init__.py
anomalylab/visualization/format.py
tests/__init__.py
AnomalyLab-0.1.2.dist-info/LICENSE
AnomalyLab-0.1.2.dist-info/METADATA
AnomalyLab-0.1.2.dist-info/WHEEL
AnomalyLab-0.1.2.dist-info/top_level.txt
AnomalyLab-0.1.2.dist-info/RECORD
